uagents_composio_adapter/__init__.py
uagents_composio_adapter/core.py
uagents_composio_adapter/py.typed
uagents_composio_adapter-1.0.8.dist-info/METADATA
uagents_composio_adapter-1.0.8.dist-info/WHEEL
uagents_composio_adapter-1.0.8.dist-info/licenses/LICENSE
uagents_composio_adapter-1.0.8.dist-info/RECORD
