Metadata-Version: 2.4
Name: uagents-composio-adapter
Version: 1.0.8
Summary: Production-ready Composio integration module for uAgents framework with LangChain-based AI agents
Project-URL: Homepage, https://github.com/tejus3131/uagents-composio-adapter
Project-URL: Repository, https://github.com/tejus3131/uagents-composio-adapter
Project-URL: Documentation, https://github.com/tejus3131/uagents-composio-adapter#readme
Author-email: Tejus Gupta <tejus3131@gmail.com>
License: MIT
License-File: LICENSE
Keywords: agents,ai,automation,composio,langchain,tools,uagents
Classifier: Development Status :: 4 - Beta
Classifier: Framework :: AsyncIO
Classifier: Intended Audience :: Developers
Classifier: License :: OSI Approved :: MIT License
Classifier: Operating System :: OS Independent
Classifier: Programming Language :: Python :: 3
Classifier: Programming Language :: Python :: 3.10
Classifier: Programming Language :: Python :: 3.11
Classifier: Programming Language :: Python :: 3.12
Classifier: Programming Language :: Python :: 3.13
Classifier: Topic :: Communications :: Chat
Classifier: Topic :: Internet :: WWW/HTTP :: Dynamic Content
Classifier: Topic :: Office/Business :: Groupware
Classifier: Topic :: Scientific/Engineering :: Artificial Intelligence
Classifier: Topic :: Software Development :: Libraries :: Python Modules
Classifier: Typing :: Typed
Requires-Python: >=3.10
Requires-Dist: composio-langchain>=0.8.14
Requires-Dist: composio>=0.8.16
Requires-Dist: langchain-openai>=0.3.33
Requires-Dist: langchain==1.0.0a10
Requires-Dist: langgraph-checkpoint-postgres>=2.0.24
Requires-Dist: langgraph>=0.6.8
Requires-Dist: psycopg[pool]>=3.2.10
Requires-Dist: pydantic>=2.0.0
Requires-Dist: uagents>=0.22.10
Provides-Extra: dev
Requires-Dist: black>=23.0.0; extra == 'dev'
Requires-Dist: build>=1.3.0; extra == 'dev'
Requires-Dist: isort>=5.12.0; extra == 'dev'
Requires-Dist: mypy>=1.0.0; extra == 'dev'
Requires-Dist: pre-commit>=4.3.0; extra == 'dev'
Requires-Dist: pytest-asyncio>=1.2.0; extra == 'dev'
Requires-Dist: pytest-cov>=7.0.0; extra == 'dev'
Requires-Dist: pytest>=8.4.2; extra == 'dev'
Requires-Dist: python-dotenv>=1.1.1; extra == 'dev'
Requires-Dist: ruff>=0.1.0; extra == 'dev'
Requires-Dist: twine>=6.2.0; extra == 'dev'
